ggame/__init__.py
ggame/__version__.py
ggame/app.py
ggame/asset.py
ggame/astro.py
ggame/bunny.png
ggame/circle.py
ggame/event.py
ggame/headlessdeps.py
ggame/indicator.py
ggame/input.py
ggame/inputpoint.py
ggame/label.py
ggame/line.py
ggame/logic.py
ggame/mathapp.py
ggame/point.py
ggame/pygamedeps.py
ggame/slider.py
ggame/sound.py
ggame/sprite.py
ggame/sysdeps.py
ggame/timer.py
ggame/images/button-round.png
ggame/images/button.png
ggame/images/red-led-off-on.png
ggame/images/rocket.png
ggame/images/toggle-up-down.png
ggame-1.1.3.dist-info/LICENSE
ggame-1.1.3.dist-info/METADATA
ggame-1.1.3.dist-info/WHEEL
ggame-1.1.3.dist-info/top_level.txt
ggame-1.1.3.dist-info/RECORD
