Metadata-Version: 2.1
Name: ggame
Version: 1.1.3
Summary: A lightweight sprite-based game and graphics framework
Home-page: https://github.com/BrythonServer/ggame
Author: Eric Dennison
Author-email: ericd@netdenizen.com
Classifier: Programming Language :: Python :: 3
Classifier: License :: OSI Approved :: MIT License
Classifier: Operating System :: OS Independent
Requires-Python: >=3.11
License-File: LICENSE
